zulipterminal/__init__.py
zulipterminal/api_types.py
zulipterminal/core.py
zulipterminal/helper.py
zulipterminal/model.py
zulipterminal/platform_code.py
zulipterminal/server_url.py
zulipterminal/ui.py
zulipterminal/unicode_emojis.py
zulipterminal/urwid_types.py
zulipterminal/version.py
zulipterminal/cli/__init__.py
zulipterminal/cli/run.py
zulipterminal/config/__init__.py
zulipterminal/config/color.py
zulipterminal/config/keys.py
zulipterminal/config/markdown_examples.py
zulipterminal/config/regexes.py
zulipterminal/config/symbols.py
zulipterminal/config/themes.py
zulipterminal/config/ui_mappings.py
zulipterminal/config/ui_sizes.py
zulipterminal/scripts/__init__.py
zulipterminal/scripts/render_symbols.py
zulipterminal/themes/__init__.py
zulipterminal/themes/colors_gruvbox.py
zulipterminal/themes/gruvbox_dark.py
zulipterminal/themes/gruvbox_light.py
zulipterminal/themes/zt_blue.py
zulipterminal/themes/zt_dark.py
zulipterminal/themes/zt_light.py
zulipterminal/ui_tools/__init__.py
zulipterminal/ui_tools/boxes.py
zulipterminal/ui_tools/buttons.py
zulipterminal/ui_tools/tables.py
zulipterminal/ui_tools/utils.py
zulipterminal/ui_tools/views.py
zulip_term-0.7.0.dist-info/LICENSE
zulip_term-0.7.0.dist-info/METADATA
zulip_term-0.7.0.dist-info/WHEEL
zulip_term-0.7.0.dist-info/entry_points.txt
zulip_term-0.7.0.dist-info/top_level.txt
zulip_term-0.7.0.dist-info/zip-safe
zulip_term-0.7.0.dist-info/RECORD
