Metadata-Version: 2.1
Name: zulip-term
Version: 0.7.0
Summary: Zulip's official terminal client
Home-page: https://github.com/zulip/zulip-terminal
Author: Zulip Open Source Project
Author-email: zulip-devel@googlegroups.com
License: UNKNOWN
Project-URL: Changelog, https://github.com/zulip/zulip-terminal/blob/main/CHANGELOG.md
Project-URL: FAQs, https://github.com/zulip/zulip-terminal/blob/main/docs/FAQ.md
Project-URL: Issues, https://github.com/zulip/zulip-terminal/issues
Project-URL: Hot Keys, https://github.com/zulip/zulip-terminal/blob/main/docs/hotkeys.md
Platform: UNKNOWN
Classifier: Development Status :: 4 - Beta
Classifier: Intended Audience :: End Users/Desktop
Classifier: Topic :: Communications :: Chat
Classifier: License :: OSI Approved :: Apache Software License
Classifier: Programming Language :: Python :: 3
Classifier: Programming Language :: Python :: 3.6
Classifier: Programming Language :: Python :: 3.7
Classifier: Programming Language :: Python :: 3.8
Classifier: Programming Language :: Python :: 3.9
Classifier: Programming Language :: Python :: 3.10
Classifier: Programming Language :: Python :: Implementation :: CPython
Classifier: Programming Language :: Python :: Implementation :: PyPy
Requires-Python: >=3.6, <3.11
Requires-Dist: beautifulsoup4 (>=4.10.0)
Requires-Dist: lxml (>=4.7.1)
Requires-Dist: pygments (>=2.11.2)
Requires-Dist: pyperclip (>=1.8.1)
Requires-Dist: python-dateutil (>=2.8.2)
Requires-Dist: pytz (>=2022.1)
Requires-Dist: typing-extensions (>=3.7)
Requires-Dist: tzlocal (>=2.1)
Requires-Dist: urwid-readline (>=0.13)
Requires-Dist: urwid (~=2.1.2)
Requires-Dist: zulip (>=0.8.2)
Provides-Extra: dev
Requires-Dist: autoflake (~=1.4.0) ; extra == 'dev'
Requires-Dist: autopep8 (~=1.6.0) ; extra == 'dev'
Requires-Dist: black (>=22.1.0) ; extra == 'dev'
Requires-Dist: flake8-continuation (~=1.0.5) ; extra == 'dev'
Requires-Dist: flake8-quotes (~=3.2.0) ; extra == 'dev'
Requires-Dist: flake8 (~=4.0.1) ; extra == 'dev'
Requires-Dist: gitlint (>=0.17) ; extra == 'dev'
Requires-Dist: isort (~=5.10.1) ; extra == 'dev'
Requires-Dist: lxml-stubs ; extra == 'dev'
Requires-Dist: mypy (==0.942) ; extra == 'dev'
Requires-Dist: pudb (==2022.1.1) ; extra == 'dev'
Requires-Dist: pytest-cov (~=2.11.1) ; extra == 'dev'
Requires-Dist: pytest-mock (~=3.6.0) ; extra == 'dev'
Requires-Dist: pytest (~=6.2.3) ; extra == 'dev'
Requires-Dist: snakeviz (>=2.1.1) ; extra == 'dev'
Requires-Dist: types-pygments ; extra == 'dev'
Requires-Dist: types-python-dateutil ; extra == 'dev'
Requires-Dist: types-pytz ; extra == 'dev'
Requires-Dist: types-requests ; extra == 'dev'
Requires-Dist: types-tzlocal ; extra == 'dev'
Provides-Extra: linting
Requires-Dist: black (>=22.1.0) ; extra == 'linting'
Requires-Dist: flake8-continuation (~=1.0.5) ; extra == 'linting'
Requires-Dist: flake8-quotes (~=3.2.0) ; extra == 'linting'
Requires-Dist: flake8 (~=4.0.1) ; extra == 'linting'
Requires-Dist: isort (~=5.10.1) ; extra == 'linting'
Provides-Extra: testing
Requires-Dist: pytest-cov (~=2.11.1) ; extra == 'testing'
Requires-Dist: pytest-mock (~=3.6.0) ; extra == 'testing'
Requires-Dist: pytest (~=6.2.3) ; extra == 'testing'
Provides-Extra: typing
Requires-Dist: lxml-stubs ; extra == 'typing'
Requires-Dist: mypy (==0.942) ; extra == 'typing'
Requires-Dist: types-pygments ; extra == 'typing'
Requires-Dist: types-python-dateutil ; extra == 'typing'
Requires-Dist: types-pytz ; extra == 'typing'
Requires-Dist: types-requests ; extra == 'typing'
Requires-Dist: types-tzlocal ; extra == 'typing'
